deli/__init__.py
deli/_hamming.py
deli/_logging.py
deli/analysis/__init__.py
deli/analysis/analysis_parse.py
deli/analysis/analysis_report_gen.py
deli/analysis/analyzers/__init__.py
deli/analysis/analyzers/gnn_analyzer.py
deli/analysis/cube_class.py
deli/analysis/gnn.py
deli/analysis/poly_o.py
deli/analysis_config.yaml
deli/cli.py
deli/configure.py
deli/decode/__init__.py
deli/decode/bb_calling.py
deli/decode/calls.py
deli/decode/decoder.py
deli/decode/degen.py
deli/decode/demultiplex.py
deli/decode/lib_calling.py
deli/decode/report.py
deli/decode/runner.py
deli/decode/umi.py
deli/dels/__init__.py
deli/dels/barcode.py
deli/dels/building_block.py
deli/dels/compound.py
deli/dels/library.py
deli/dels/reaction.py
deli/dels/selection.py
deli/dels/umi.py
deli/design/__init__.py
deli/design/barcode/__init__.py
deli/design/barcode/tag_factory.py
deli/dna/__init__.py
deli/dna/align.py
deli/dna/io.py
deli/py.typed
deli/templates/analysis_report.html
deli/templates/decode_report.html
deli/tmp_DEL6_files/building_block_a.json
deli/tmp_DEL6_files/building_block_b.json
deli/tmp_DEL6_files/building_block_c.json
deli/tmp_DEL6_files/del6.json
deli/utils/__init__.py
deli/utils/distance_utils.py
deli/utils/mol_utils.py
deli_chem-0.1.2.dist-info/METADATA
deli_chem-0.1.2.dist-info/WHEEL
deli_chem-0.1.2.dist-info/entry_points.txt
deli_chem-0.1.2.dist-info/licenses/LICENSE.txt
deli_chem-0.1.2.dist-info/RECORD
