Metadata-Version: 2.4
Name: deli-chem
Version: 0.1.2
Summary: DNA encoded library sequence analysis software with custom library design support
License-Expression: MIT
License-File: LICENSE.txt
Keywords: DNA-encoded library,DEL,cheminformatics,bioinformatics,drug discovery
Author: James Wellnitz
Author-email: wellnitz.james@gmail.com
Maintainer: James Wellnitz
Maintainer-email: wellnitz.james@gmail.com
Requires-Python: >=3.10,<4.0
Classifier: Natural Language :: English
Classifier: Operating System :: OS Independent
Classifier: Development Status :: 3 - Alpha
Classifier: Intended Audience :: Science/Research
Classifier: Topic :: Scientific/Engineering :: Bio-Informatics
Classifier: License :: OSI Approved :: MIT License
Provides-Extra: ml
Requires-Dist: Jinja2 (>=3.1.3)
Requires-Dist: Levenshtein (>=0.25.0)
Requires-Dist: biopython (==1.85)
Requires-Dist: click (>=8.1.3)
Requires-Dist: cutadapt (==5.0)
Requires-Dist: dnaio (==1.2.3)
Requires-Dist: matplotlib (>=3.9.3)
Requires-Dist: matplotlib-venn (==0.11.10)
Requires-Dist: numba (>=0.60.0)
Requires-Dist: numpy (<2.0)
Requires-Dist: pandas (>=2.2.3)
Requires-Dist: plotly (>=5.20.0)
Requires-Dist: polars (>=0.20.10)
Requires-Dist: pytorch-lightning (>=2.0.0) ; extra == "ml"
Requires-Dist: pyyaml (==6.0.2)
Requires-Dist: rdkit (>=2024.9.5)
Requires-Dist: scikit-learn (>=1.4.2)
Requires-Dist: scipy (>=1.14.1)
Requires-Dist: seaborn (>=0.12.2)
Requires-Dist: torch (>=2.2.0) ; extra == "ml"
Requires-Dist: torch-geometric (==2.6.1) ; extra == "ml"
Requires-Dist: torchaudio (>=2.2.0) ; extra == "ml"
Requires-Dist: torchvision (>=0.17.0) ; extra == "ml"
Requires-Dist: tqdm (>=4.66.4)
Requires-Dist: typing-extensions (>=4.0.0)
Project-URL: Homepage, https://github.com/Popov-Lab-UNC/DELi
Project-URL: Issues, https://github.com/Popov-Lab-UNC/DELi/issues
Project-URL: Repository, https://github.com/Popov-Lab-UNC/DELi
